Metadata-Version: 1.0
Name: quadsolver
Version: 0.12
Summary: solves quadratic equations
Home-page: UNKNOWN
Author: UNKNOWN
Author-email: UNKNOWN
License: UNKNOWN
Platform: UNKNOWN
